manhole.pth
manhole/__init__.py
manhole/cli.py
manhole-1.8.0.dist-info/AUTHORS.rst
manhole-1.8.0.dist-info/LICENSE
manhole-1.8.0.dist-info/METADATA
manhole-1.8.0.dist-info/WHEEL
manhole-1.8.0.dist-info/entry_points.txt
manhole-1.8.0.dist-info/top_level.txt
manhole-1.8.0.dist-info/RECORD
