Metadata-Version: 1.2
Name: manhole
Version: 1.8.0
Summary: Manhole is in-process service that will accept unix domain socket connections and present the
Home-page: https://github.com/ionelmc/python-manhole
Author: Ionel Cristian Mărieș
Author-email: contact@ionelmc.ro
License: BSD 2-Clause License
Project-URL: Documentation, https://python-manhole.readthedocs.io/
Project-URL: Changelog, https://python-manhole.readthedocs.io/en/latest/changelog.html
Project-URL: Issue Tracker, https://github.com/ionelmc/python-manhole/issues
Keywords: debugging,manhole,thread,socket,unix domain socket
Platform: UNKNOWN
Classifier: Development Status :: 5 - Production/Stable
Classifier: Intended Audience :: Developers
Classifier: License :: OSI Approved :: BSD License
Classifier: Operating System :: Unix
Classifier: Operating System :: POSIX
Classifier: Programming Language :: Python
Classifier: Topic :: Software Development :: Debuggers
Classifier: Topic :: Utilities
Classifier: Topic :: System :: Monitoring
Classifier: Topic :: System :: Networking
Classifier: Programming Language :: Python :: 2.7
Classifier: Programming Language :: Python :: 3
Classifier: Programming Language :: Python :: 3.4
Classifier: Programming Language :: Python :: 3.5
Classifier: Programming Language :: Python :: 3.6
Classifier: Programming Language :: Python :: 3.7
Classifier: Programming Language :: Python :: Implementation :: CPython
Classifier: Programming Language :: Python :: Implementation :: PyPy
Classifier: Topic :: Utilities
Requires-Python: >=2.7, !=3.0.*, !=3.1.*, !=3.2.*, !=3.3.*, !=3.4.*
